odoo/addons/account_brand/README.rst
odoo/addons/account_brand/__init__.py
odoo/addons/account_brand/__manifest__.py
odoo/addons/account_brand/i18n/account_brand.pot
odoo/addons/account_brand/i18n/de.po
odoo/addons/account_brand/i18n/es.po
odoo/addons/account_brand/i18n/hr.po
odoo/addons/account_brand/i18n/nl.po
odoo/addons/account_brand/i18n/zh_CN.po
odoo/addons/account_brand/models/__init__.py
odoo/addons/account_brand/models/account_move.py
odoo/addons/account_brand/models/res_partner_account_brand.py
odoo/addons/account_brand/readme/CONFIGURE.rst
odoo/addons/account_brand/readme/CONTRIBUTORS.rst
odoo/addons/account_brand/readme/CREDITS.rst
odoo/addons/account_brand/readme/DESCRIPTION.rst
odoo/addons/account_brand/readme/USAGE.rst
odoo/addons/account_brand/security/res_partner_account_brand.xml
odoo/addons/account_brand/static/description/icon.png
odoo/addons/account_brand/static/description/index.html
odoo/addons/account_brand/tests/__init__.py
odoo/addons/account_brand/tests/test_account_analytic_move.py
odoo/addons/account_brand/tests/test_account_move.py
odoo/addons/account_brand/tests/test_brand_mixin.py
odoo/addons/account_brand/views/account_move_views.xml
odoo/addons/account_brand/views/res_partner_account_brand.xml
odoo/addons/account_brand/wizards/__init__.py
odoo/addons/account_brand/wizards/account_move_reversal.py
odoo14_addon_account_brand-14.0.1.0.2.dist-info/METADATA
odoo14_addon_account_brand-14.0.1.0.2.dist-info/WHEEL
odoo14_addon_account_brand-14.0.1.0.2.dist-info/top_level.txt
odoo14_addon_account_brand-14.0.1.0.2.dist-info/RECORD
